{
  "name": "Agasteer",
  "catch": "Free yourself from the fear of data loss",
  "description": "Always pulls on startup. GitHub is the single source of truth. Conflicts are theoretically impossible.",
  "theme": {"bg": "#121212", "fg": "#ffffff", "accent": "#4ade80", "muted": "#86efac"},
  "links": {"play": "https://agasteer.llll-ll.com/", "github": "https://github.com/kako-jun/agasteer"},
  "og": {"title": "Agasteer", "description": "The Markdown app that never conflicts"},
  "gallery": ["gallery/slide1.webp", "gallery/slide2.webp", "gallery/slide3.webp"],
  "features": [
    {"title": "No conflicts. Ever.", "description": "Always pulls on startup. GitHub is truth. Safe across multiple devices.", "image": "hero.webp"},
    {"title": "Direct to GitHub", "description": "No middleman server. Saves straight to your repo. Your data, your control.", "image": "hero.webp"},
    {"title": "Vim mode!", "description": "Navigate with hjkl. Keyboard-only fastest note-taking experience.", "image": "hero.webp"},
    {"title": "Ruled-line mode!", "description": "Looks just like a real notebook. Why doesn't everyone have this?", "image": "hero.webp"}
  ],
  "author": {"name": "kako-jun"}
}
